README.md
setup.cfg
setup.py
openai_agent_llm/__init__.py
openai_agent_llm/constants.py
openai_agent_llm/protocol.py
openai_agent_llm.egg-info/PKG-INFO
openai_agent_llm.egg-info/SOURCES.txt
openai_agent_llm.egg-info/dependency_links.txt
openai_agent_llm.egg-info/requires.txt
openai_agent_llm.egg-info/top_level.txt
openai_agent_llm.egg-info/zip-safe