Metadata-Version: 2.1
Name: openai-agent-llm
Version: 0.0.2
Summary: Customize the LLM interface to make it compatible with the openai interface
Home-page: https://github.com/lijiacaigit/openai-agent
Author: Lijiacai
Author-email: 1050518702@qq.com
License: UNKNOWN
Platform: UNKNOWN
Classifier: Programming Language :: Python :: 3
Classifier: License :: OSI Approved :: MIT License
Classifier: Operating System :: OS Independent
Requires-Python: >=3.7.1
